tdd_llm/__init__.py
tdd_llm/cli.py
tdd_llm/config.py
tdd_llm/converter.py
tdd_llm/deployer.py
tdd_llm/migrate.py
tdd_llm/paths.py
tdd_llm/placeholder.py
tdd_llm/updater.py
tdd_llm/backends/__init__.py
tdd_llm/backends/base.py
tdd_llm/backends/files.py
tdd_llm/backends/jira/__init__.py
tdd_llm/backends/jira/auth.py
tdd_llm/backends/jira/backend.py
tdd_llm/backends/jira/client.py
tdd_llm/templates/manifest.json
tdd_llm/templates/commands/tdd/create/epic.md
tdd_llm/templates/commands/tdd/create/story.md
tdd_llm/templates/commands/tdd/flow/1-analyze.md
tdd_llm/templates/commands/tdd/flow/2-test.md
tdd_llm/templates/commands/tdd/flow/3-dev.md
tdd_llm/templates/commands/tdd/flow/4-docs.md
tdd_llm/templates/commands/tdd/flow/5-review.md
tdd_llm/templates/commands/tdd/flow/6-done.md
tdd_llm/templates/commands/tdd/flow/status.md
tdd_llm/templates/commands/tdd/init/1-project.md
tdd_llm/templates/commands/tdd/init/2-architecture.md
tdd_llm/templates/commands/tdd/init/3-standards.md
tdd_llm/templates/commands/tdd/init/4-readme.md
tdd_llm/templates/placeholders/backends/files/ARCHIVE_CONTEXT.md
tdd_llm/templates/placeholders/backends/files/BRANCH_FORMAT.md
tdd_llm/templates/placeholders/backends/files/CREATE_EPIC.md
tdd_llm/templates/placeholders/backends/files/CREATE_STORY.md
tdd_llm/templates/placeholders/backends/files/EPIC_SOURCE.md
tdd_llm/templates/placeholders/backends/files/GET_TRANSITIONS.md
tdd_llm/templates/placeholders/backends/files/LIST_COMMENTS.md
tdd_llm/templates/placeholders/backends/files/LIST_EPICS.md
tdd_llm/templates/placeholders/backends/files/LIST_STORIES.md
tdd_llm/templates/placeholders/backends/files/SEARCH.md
tdd_llm/templates/placeholders/backends/files/STATE_COMMIT.md
tdd_llm/templates/placeholders/backends/files/STATE_READ.md
tdd_llm/templates/placeholders/backends/files/STATE_SOURCE.md
tdd_llm/templates/placeholders/backends/files/STATE_UPDATE.md
tdd_llm/templates/placeholders/backends/files/TASK_SOURCE.md
tdd_llm-0.8.1.dist-info/METADATA
tdd_llm-0.8.1.dist-info/WHEEL
tdd_llm-0.8.1.dist-info/entry_points.txt
tdd_llm-0.8.1.dist-info/RECORD
