Metadata-Version: 2.4
Name: tdd-llm
Version: 0.8.1
Summary: Deploy TDD workflow templates for Claude and Gemini AI assistants
Project-URL: Homepage, https://github.com/mxdumas/tdd-llm-workflow
Project-URL: Repository, https://github.com/mxdumas/tdd-llm-workflow
License-Expression: MIT
Keywords: ai,claude,gemini,tdd,templates,workflow
Classifier: Development Status :: 3 - Alpha
Classifier: Environment :: Console
Classifier: Intended Audience :: Developers
Classifier: License :: OSI Approved :: MIT License
Classifier: Operating System :: OS Independent
Classifier: Programming Language :: Python :: 3
Classifier: Programming Language :: Python :: 3.10
Classifier: Programming Language :: Python :: 3.11
Classifier: Programming Language :: Python :: 3.12
Classifier: Topic :: Software Development
Requires-Python: >=3.10
Requires-Dist: cryptography>=41.0.0
Requires-Dist: httpx>=0.25.0
Requires-Dist: pyyaml>=6.0
Requires-Dist: rich>=13.0
Requires-Dist: typer>=0.9.0
Provides-Extra: dev
Requires-Dist: pre-commit>=3.0; extra == 'dev'
Requires-Dist: pytest-cov>=4.0; extra == 'dev'
Requires-Dist: pytest>=7.0; extra == 'dev'
Requires-Dist: ruff>=0.1.0; extra == 'dev'
